MANIFEST.in
README.md
license.txt
setup.py
processbar/__init__.py
processbar/simpleprocessbar.py
processbar.egg-info/PKG-INFO
processbar.egg-info/SOURCES.txt
processbar.egg-info/dependency_links.txt
processbar.egg-info/top_level.txt